rvs/__init__.py
rvs/__main__.py
rvs/cli.py
rvs/exceptions.py
rvs/commands/__init__.py
rvs/commands/add.py
rvs/commands/base.py
rvs/commands/branch.py
rvs/commands/checkout.py
rvs/commands/commit.py
rvs/commands/diff.py
rvs/commands/diff_tree.py
rvs/commands/init.py
rvs/commands/log.py
rvs/commands/ls_files.py
rvs/commands/ls_tree.py
rvs/commands/merge.py
rvs/commands/mv.py
rvs/commands/rebase.py
rvs/commands/reset.py
rvs/commands/restore.py
rvs/commands/rm.py
rvs/commands/show.py
rvs/commands/stash.py
rvs/commands/status.py
rvs/commands/switch.py
rvs/commands/worktree.py
rvs/core/__init__.py
rvs/core/hooks.py
rvs/core/index.py
rvs/core/objects.py
rvs/core/refs.py
rvs/core/repository.py
rvs-2.1.1.dist-info/licenses/LICENSE
rvs-2.1.1.dist-info/METADATA
rvs-2.1.1.dist-info/WHEEL
rvs-2.1.1.dist-info/entry_points.txt
rvs-2.1.1.dist-info/top_level.txt
rvs-2.1.1.dist-info/RECORD
