Metadata-Version: 2.4
Name: rvs
Version: 2.1.1
Summary: Robust Versioning System - Git-style version control built for universal compatibility
Home-page: https://github.com/rvs-rvs/rvs
Author: rvs-rvs
Author-email: mailto.rvs@usa.com
Project-URL: Bug Reports, https://github.com/rvs-rvs/rvs/issues
Project-URL: Source, https://github.com/rvs-rvs/rvs
Project-URL: Documentation, https://github.com/rvs-rvs/rvs#readme
Keywords: python git version-control python-3 pypi rvs vcs cli robust portable
Classifier: Development Status :: 4 - Beta
Classifier: Intended Audience :: Developers
Classifier: Programming Language :: Python :: 3
Classifier: Programming Language :: Python :: 3.6
Classifier: Programming Language :: Python :: 3.7
Classifier: Programming Language :: Python :: 3.8
Classifier: Programming Language :: Python :: 3.9
Classifier: Programming Language :: Python :: 3.10
Classifier: Programming Language :: Python :: 3.11
Classifier: Programming Language :: Python :: 3.12
Classifier: Topic :: Software Development :: Version Control
Classifier: Topic :: Software Development :: Libraries :: Python Modules
Classifier: Environment :: Console
Classifier: Operating System :: OS Independent
Requires-Python: >=3.6
License-File: LICENSE
Dynamic: author
Dynamic: author-email
Dynamic: classifier
Dynamic: description
Dynamic: description-content-type
Dynamic: home-page
Dynamic: keywords
Dynamic: license-file
Dynamic: project-url
Dynamic: requires-python
Dynamic: summary
